{
  "prepare_queue": {
    "installed": [],
    "uninstalled": []
  },
  "config_munge": {
    "files": {}
  },
  "installed_plugins": {
    "cordova-custom-config": {
      "PACKAGE_NAME": "org.trmn.medusa"
    },
    "cordova-plugin-android-permissions": {
      "PACKAGE_NAME": "org.trmn.medusa"
    },
    "cordova-plugin-app-version": {
      "PACKAGE_NAME": "org.trmn.medusa"
    },
    "cordova-plugin-camera": {
      "PACKAGE_NAME": "org.trmn.medusa"
    },
    "cordova-plugin-console": {
      "PACKAGE_NAME": "org.trmn.medusa"
    },
    "cordova-plugin-device": {
      "PACKAGE_NAME": "org.trmn.medusa"
    },
    "cordova-plugin-dialogs": {
      "PACKAGE_NAME": "org.trmn.medusa"
    },
    "cordova-plugin-file-transfer": {
      "PACKAGE_NAME": "org.trmn.medusa"
    },
    "cordova-plugin-inappbrowser": {
      "PACKAGE_NAME": "org.trmn.medusa"
    },
    "cordova-plugin-screen-orientation": {
      "PACKAGE_NAME": "org.trmn.medusa"
    },
    "cordova-plugin-spinner": {
      "PACKAGE_NAME": "org.trmn.medusa"
    },
    "cordova-plugin-splashscreen": {
      "PACKAGE_NAME": "org.trmn.medusa"
    },
    "cordova-plugin-statusbar": {
      "PACKAGE_NAME": "org.trmn.medusa"
    },
    "cordova-plugin-whitelist": {
      "PACKAGE_NAME": "org.trmn.medusa"
    },
    "phonegap-plugin-barcodescanner": {
      "CAMERA_USAGE_DESCRIPTION": "To scan barcodes and take profile pictures",
      "PACKAGE_NAME": "org.trmn.medusa"
    }
  },
  "dependent_plugins": {
    "cordova-plugin-compat": {
      "PACKAGE_NAME": "org.trmn.medusa"
    },
    "cordova-plugin-file": {
      "PACKAGE_NAME": "org.trmn.medusa"
    }
  }
}